fABBA/__init__.py
fABBA/aggregation.py
fABBA/caggregation.cp38-win_amd64.pyd
fABBA/caggregation_memview.cp38-win_amd64.pyd
fABBA/chainApproximation.py
fABBA/chainApproximation_c.cp38-win_amd64.pyd
fABBA/digitization.py
fABBA/load_datasets.py
fABBA/symbolic_representation.py
fABBA-0.2.1.dist-info/LICENSE
fABBA-0.2.1.dist-info/METADATA
fABBA-0.2.1.dist-info/WHEEL
fABBA-0.2.1.dist-info/top_level.txt
fABBA-0.2.1.dist-info/RECORD
