Metadata-Version: 2.1
Name: fABBA
Version: 0.2.1
Summary: An efficient aggregation based symbolic representation
Home-page: https://github.com/nla-group/fABBA
Author: Stefan Guettel, Xinye Chen
Author-email: stefan.guettel@manchester.ac.uk
License: BSD 3-Clause
Platform: UNKNOWN
License-File: LICENSE
Requires-Dist: numpy
